jupyter_kernel_executor/__init__.py
jupyter_kernel_executor/_version.py
jupyter_kernel_executor/file_watcher.py
jupyter_kernel_executor/fileid.py
jupyter_kernel_executor/handlers.py
jupyter_kernel_executor/tests/__init__.py
jupyter_kernel_executor/tests/test.ipynb
jupyter_kernel_executor/tests/test_handlers.py
jupyter_kernel_executor/tests/test_with_fileid.py
jupyter_kernel_executor/tests/utils.py
jupyter_kernel_executor-0.2.4.data/data/etc/jupyter/jupyter_notebook_config.d/jupyter_kernel_executor.json
jupyter_kernel_executor-0.2.4.data/data/etc/jupyter/jupyter_server_config.d/jupyter_kernel_executor.json
jupyter_kernel_executor-0.2.4.data/data/share/jupyter/labextensions/jupyter_kernel_executor/package.json
jupyter_kernel_executor-0.2.4.data/data/share/jupyter/labextensions/jupyter_kernel_executor/static/568.6ab5a238375420d054d7.js
jupyter_kernel_executor-0.2.4.data/data/share/jupyter/labextensions/jupyter_kernel_executor/static/747.840491d1d3244658f4d1.js
jupyter_kernel_executor-0.2.4.data/data/share/jupyter/labextensions/jupyter_kernel_executor/static/remoteEntry.180528eb05c70fc152ea.js
jupyter_kernel_executor-0.2.4.data/data/share/jupyter/labextensions/jupyter_kernel_executor/static/style.js
jupyter_kernel_executor-0.2.4.data/data/share/jupyter/labextensions/jupyter_kernel_executor/static/third-party-licenses.json
jupyter_kernel_executor-0.2.4.data/data/share/jupyter/labextensions/jupyter_kernel_executor/install.json
jupyter_kernel_executor-0.2.4.dist-info/METADATA
jupyter_kernel_executor-0.2.4.dist-info/WHEEL
jupyter_kernel_executor-0.2.4.dist-info/licenses/LICENSE
jupyter_kernel_executor-0.2.4.dist-info/RECORD
