Metadata-Version: 2.1
Name: jupyter_kernel_executor
Version: 0.2.4
Summary: jupyter extension for http cell execute
Project-URL: Homepage, https://github.com/wh1isper/jupyter_kernel_executor
Project-URL: Bug Tracker, https://github.com/wh1isper/jupyter_kernel_executor/issues
Project-URL: Repository, https://github.com/wh1isper/jupyter_kernel_executor.git
Author-email: wh1isper <9537586@qq.com>
License: BSD 3-Clause License
License-File: LICENSE
Classifier: Framework :: Jupyter
Classifier: Framework :: Jupyter :: JupyterLab
Classifier: Framework :: Jupyter :: JupyterLab :: 3
Classifier: Framework :: Jupyter :: JupyterLab :: Extensions
Classifier: Framework :: Jupyter :: JupyterLab :: Extensions :: Prebuilt
Classifier: License :: OSI Approved :: BSD License
Classifier: Programming Language :: Python
Classifier: Programming Language :: Python :: 3
Classifier: Programming Language :: Python :: 3.7
Classifier: Programming Language :: Python :: 3.8
Classifier: Programming Language :: Python :: 3.9
Classifier: Programming Language :: Python :: 3.10
Classifier: Programming Language :: Python :: 3.11
Requires-Python: >=3.7
Requires-Dist: jupyter-kernel-client
Requires-Dist: jupyter-server<3,>=1.6
Requires-Dist: watchfiles
Provides-Extra: fileid
Requires-Dist: jupyter-server-fileid==0.6.0; extra == 'fileid'
Provides-Extra: test
Requires-Dist: coverage; extra == 'test'
Requires-Dist: nbformat; extra == 'test'
Requires-Dist: pytest; extra == 'test'
Requires-Dist: pytest-asyncio; extra == 'test'
Requires-Dist: pytest-cov; extra == 'test'
Requires-Dist: pytest-tornasync; extra == 'test'
